server_status/__init__.py
server_status/urls.py
server_status/views.py
server_status/views_test.py
server_status/static/.empty
server_status/static/server_status/.empty
server_status/tests/__init__.py
server_status/tests/settings.py
server_status/tests/urls.py
server_status/tests/test_app/__init__.py
server_status/tests/test_app/models.py
server_status/tests/test_app/templates/400.html
server_status/tests/test_app/templates/500.html
django_server_status-0.7.3.dist-info/LICENSE
django_server_status-0.7.3.dist-info/METADATA
django_server_status-0.7.3.dist-info/WHEEL
django_server_status-0.7.3.dist-info/top_level.txt
django_server_status-0.7.3.dist-info/RECORD
