Metadata-Version: 2.1
Name: django-server-status
Version: 0.7.3
Summary: Monitor server status with a healthcheck.
Requires-Dist: django
